MANIFEST.in
README.rst
setup.py
django_piwik.egg-info/PKG-INFO
django_piwik.egg-info/SOURCES.txt
django_piwik.egg-info/dependency_links.txt
django_piwik.egg-info/not-zip-safe
django_piwik.egg-info/requires.txt
django_piwik.egg-info/top_level.txt
piwik/__init__.py
piwik/templates/piwik/tracking_code.html
piwik/templatetags/__init__.py
piwik/templatetags/piwik_tags.py