Metadata-Version: 1.0
Name: django-piwik
Version: 0.1
Summary: A simple app to add the Piwik JS tracking code to your template.
Home-page: https://github.com/raphaa/django-piwik
Author: Raphael Jasjukaitis
Author-email: webmaster@raphaa.de
License: BSD License
Platform: OS Independent
Classifier: Environment :: Web Environment
Classifier: License :: OSI Approved :: BSD License
Classifier: Operating System :: OS Independent
Classifier: Programming Language :: Python
Classifier: Framework :: Django
